atomsciflow/__init__.py
atomsciflow/abinit/__init__.py
atomsciflow/abinit/abinit.py
atomsciflow/abinit/io.py
atomsciflow/abinit/post.py
atomsciflow/cmd/__init__.py
atomsciflow/cmd/atomsciflow.py
atomsciflow/cmd/atomsciflow_calc.py
atomsciflow/cmd/atomsciflow_calc_abinit.py
atomsciflow/cmd/atomsciflow_calc_cp2k.py
atomsciflow/cmd/atomsciflow_calc_dalton.py
atomsciflow/cmd/atomsciflow_calc_dftbplus.py
atomsciflow/cmd/atomsciflow_calc_elk.py
atomsciflow/cmd/atomsciflow_calc_exciting.py
atomsciflow/cmd/atomsciflow_calc_gamessus.py
atomsciflow/cmd/atomsciflow_calc_gaussian.py
atomsciflow/cmd/atomsciflow_calc_gromacs.py
atomsciflow/cmd/atomsciflow_calc_lammps.py
atomsciflow/cmd/atomsciflow_calc_nwchem.py
atomsciflow/cmd/atomsciflow_calc_octopus.py
atomsciflow/cmd/atomsciflow_calc_orca.py
atomsciflow/cmd/atomsciflow_calc_qchem.py
atomsciflow/cmd/atomsciflow_calc_qe.py
atomsciflow/cmd/atomsciflow_calc_qmcpack.py
atomsciflow/cmd/atomsciflow_calc_siesta.py
atomsciflow/cmd/atomsciflow_calc_vasp.py
atomsciflow/cmd/atomsciflow_calc_xtb.py
atomsciflow/cmd/atomsciflow_post.py
atomsciflow/cmd/atomsciflow_post_abinit.py
atomsciflow/cmd/atomsciflow_post_cp2k.py
atomsciflow/cmd/atomsciflow_post_elk.py
atomsciflow/cmd/atomsciflow_post_gamessus.py
atomsciflow/cmd/atomsciflow_post_nwchem.py
atomsciflow/cmd/atomsciflow_post_octopus.py
atomsciflow/cmd/atomsciflow_post_qe.py
atomsciflow/cmd/atomsciflow_post_siesta.py
atomsciflow/cmd/atomsciflow_post_vasp.py
atomsciflow/cmd/calc_tools.py
atomsciflow/cmd/cmd_utils.py
atomsciflow/config/__init__.py
atomsciflow/cp2k/__init__.py
atomsciflow/cp2k/cp2k.py
atomsciflow/cp2k/io.py
atomsciflow/cp2k/post.py
atomsciflow/cpp/__init__.py
atomsciflow/cpp/abinit.cp39-win_amd64.pyd
atomsciflow/cpp/base.cp39-win_amd64.pyd
atomsciflow/cpp/cmd.cp39-win_amd64.pyd
atomsciflow/cpp/config.cp39-win_amd64.pyd
atomsciflow/cpp/cp2k.cp39-win_amd64.pyd
atomsciflow/cpp/cube_handle.cp39-win_amd64.pyd
atomsciflow/cpp/dalton.cp39-win_amd64.pyd
atomsciflow-0.0.1.dist-info/LICENSE
atomsciflow-0.0.1.dist-info/METADATA
atomsciflow-0.0.1.dist-info/NOTICE
atomsciflow-0.0.1.dist-info/WHEEL
atomsciflow-0.0.1.dist-info/entry_points.txt
atomsciflow-0.0.1.dist-info/top_level.txt
atomsciflow-0.0.1.dist-info/RECORD
